Bstyle/Img.py
Bstyle/Style.py
Bstyle/TitleBar.py
Bstyle/__init__.py
Bstyle-2021.9.1.1.dist-info/METADATA
Bstyle-2021.9.1.1.dist-info/WHEEL
Bstyle-2021.9.1.1.dist-info/top_level.txt
Bstyle-2021.9.1.1.dist-info/RECORD
